flask_chartjs/__init__.py
flask_chartjs/chart.py
flask_chartjs/py.typed
flask_chartjs/templates/html.jinja
flask_chartjs/templates/js.jinja
flask_chartjs/templates/load_chartjs.jinja
flask_chartjs_manager-0.1.17.dist-info/METADATA
flask_chartjs_manager-0.1.17.dist-info/WHEEL
flask_chartjs_manager-0.1.17.dist-info/top_level.txt
flask_chartjs_manager-0.1.17.dist-info/RECORD
