Metadata-Version: 2.4
Name: flask-chartjs-manager
Version: 0.1.17
Author-email: Sebastian Salinas <seba.salinas.delrio@gmail.com>
License-Expression: MIT
Project-URL: Homepage, https://github.com/sebasalinass/flask-chartjs
Requires-Python: >=3.11
Requires-Dist: flask<4,>=2
Requires-Dist: imagekitio<5,>=4
